README.md
setup.py
ecom_utils/__init__.py
ecom_utils.egg-info/PKG-INFO
ecom_utils.egg-info/SOURCES.txt
ecom_utils.egg-info/dependency_links.txt
ecom_utils.egg-info/requires.txt
ecom_utils.egg-info/top_level.txt
ecom_utils/criptografia/__init__.py
ecom_utils/criptografia/core.py
ecom_utils/pon/__init__.py
ecom_utils/pon/core.py
ecom_utils/scient/airflow/functions.py
ecom_utils/scient/airflow/core/__init__.py
ecom_utils/scient/airflow/sql/operators.py
ecom_utils/scient/airflow/sql/core/base.py
ecom_utils/scient/airflow/sql/mssql/functions.py
ecom_utils/scient/airflow/sql/mssql/operators.py
ecom_utils/scient/airflow/sql/postgres/functions.py
ecom_utils/scient/airflow/sql/postgres/operators.py
ecom_utils/tgd/__init__.py
ecom_utils/tgd/base.py
ecom_utils/tgd/core.py