Metadata-Version: 1.1
Name: ecom-utils
Version: 1.3.10
Summary: Core de módulos para PyPI
Home-page: https://git.ecom.com.ar/python-dev/ecom-utils
Author: Ecom Developers
Author-email: simono@ecom.com.ar
License: BSD
Keywords: ecom utils
Platform: UNKNOWN
Classifier: Development Status :: 1 - Planning
Classifier: License :: OSI Approved :: GNU Lesser General Public License v2 (LGPLv2)
Classifier: Programming Language :: Python
Classifier: Programming Language :: Python :: 3.7
Classifier: Topic :: Utilities
